{"type":"Box","props":{"y":0,"x":0,"width":890,"runtime":"form/ShopItem.js","presetID":1,"name":"ShopItem","isPresetRoot":true,"height":450},"compId":147,"child":[{"type":"Sprite","props":{"y":150,"x":587,"visible":false,"texture":"smallpop/wupinkuang.png","presetID":8,"name":"itemBlocked"},"compId":150,"child":[{"type":"Button","props":{"y":130,"x":135,"width":128,"stateNum":1,"presetID":9,"name":"item","height":134,"gray":true,"anchorY":0.5,"anchorX":0.5},"compId":158},{"type":"Text","props":{"y":216,"x":65,"text":"真皮红座椅","presetID":10,"fontSize":28,"color":"#676464","runtime":"laya.display.Text"},"compId":159}]},{"type":"Sprite","props":{"y":174,"x":629,"visible":false,"texture":"shopui/xiaomianban2.png","presetID":11,"name":"itemBlocked"},"compId":151},{"type":"Sprite","props":{"texture":"shopui/biaotilan.png","presetID":14},"compId":160,"child":[{"type":"Text","props":{"y":59,"x":68,"valign":"middle","text":"【咖啡店】咖啡猫窝","presetID":13,"pivotY":30,"pivotX":60,"name":"title","fontSize":50,"color":"#454040","align":"center","runtime":"laya.display.Text"},"compId":153}]}],"loadList":["smallpop/wupinkuang.png","shopui/xiaomianban2.png","shopui/biaotilan.png"],"loadList3D":[]}