{"type":"Tree","props":{"y":0,"x":0,"width":450,"presetID":1,"isPresetRoot":true,"height":400},"compId":475,"child":[{"type":"Sprite","props":{"y":94,"x":51,"texture":"component_coffee/zuodian2_1.png","presetID":2,"width":230,"name":"dropPoint","height":230},"compId":476},{"type":"Box","props":{"y":-23,"x":0,"width":400,"var":"buildingRoot_0","presetID":3,"name":"buildingRoot_0","height":400},"compId":477},{"type":"Text","props":{"y":38,"x":51,"var":"move_0","text":"rest1:rest2","scaleY":0,"scaleX":0,"presetID":4,"name":"move_0","runtime":"laya.display.Text"},"compId":478},{"type":"Tree","props":{"y":163,"x":189,"width":230,"presetID":5,"name":"dropPoint","height":230},"compId":480}],"loadList":["component_coffee/zuodian2_1.png"],"loadList3D":[]}